{
  "timestamp": "2025-08-21T22:39:50.398Z",
  "query": "Anwendungsfehler verwalten",
  "expandedQuery": "",
  "commandLineOptions": {
    "verbose": false,
    "inspectOnly": false,
    "lowerThreshold": true,
    "expandQuery": false,
    "samplePoints": false
  },
  "flow": [
    {
      "name": "FLOW_START",
      "timestamp": "2025-08-21T22:39:50.412Z",
      "details": {
        "query": "Anwendungsfehler verwalten"
      }
    },
    {
      "name": "CS30_CHECK_START",
      "timestamp": "2025-08-21T22:39:50.412Z",
      "details": "Checking CS30 collection availability"
    },
    {
      "name": "CS30_CHECK_COMPLETE",
      "timestamp": "2025-08-21T22:39:50.442Z",
      "details": {
        "isAvailable": true
      }
    },
    {
      "name": "CS30_COLLECTION_INFO",
      "timestamp": "2025-08-21T22:39:50.461Z",
      "details": {
        "dimensions": 768,
        "distanceMetric": "Cosine",
        "hasIndexes": false,
        "config": {
          "params": {
            "vectors": {
              "size": 768,
              "distance": "Cosine",
              "on_disk": true
            },
            "shard_number": 1,
            "replication_factor": 1,
            "write_consistency_factor": 1,
            "on_disk_payload": true
          },
          "hnsw_config": {
            "m": 16,
            "ef_construct": 100,
            "full_scan_threshold": 10000,
            "max_indexing_threads": 0,
            "on_disk": true
          },
          "optimizer_config": {
            "deleted_threshold": 0.2,
            "vacuum_min_vector_number": 1000,
            "default_segment_number": 0,
            "max_segment_size": null,
            "memmap_threshold": null,
            "indexing_threshold": 20000,
            "flush_interval_sec": 50,
            "max_optimization_threads": null
          },
          "wal_config": {
            "wal_capacity_mb": 32,
            "wal_segments_ahead": 0
          },
          "quantization_config": null
        }
      }
    },
    {
      "name": "STANDARD_RESPONSE_GENERATION_START",
      "timestamp": "2025-08-21T22:39:50.462Z",
      "details": {
        "contextLength": 0,
        "isCs30Response": false
      }
    },
    {
      "name": "STANDARD_RESPONSE_GENERATION_COMPLETE",
      "timestamp": "2025-08-21T22:40:12.697Z",
      "details": {
        "timeMs": 22235,
        "responsePreview": "Absolut. Das Verwalten von Anwendungsfehlern ist eine zentrale und tägliche Aufgabe in der Marktkommunikation (MaKo) der Energiewirtschaft. Es sorgt dafür, dass die automatisierten Prozesse zwischen d..."
      }
    },
    {
      "name": "CS30_SEARCH_START",
      "timestamp": "2025-08-21T22:40:12.697Z",
      "details": {
        "originalQuery": "Anwendungsfehler verwalten",
        "searchQuery": "Anwendungsfehler verwalten",
        "limit": 5,
        "scoreThreshold": 0.3,
        "usingExpansion": false
      }
    },
    {
      "name": "EMBEDDING_GENERATION_START",
      "timestamp": "2025-08-21T22:40:12.697Z",
      "details": {
        "text": "Anwendungsfehler verwalten..."
      }
    },
    {
      "name": "EMBEDDING_GENERATION_COMPLETE",
      "timestamp": "2025-08-21T22:40:12.980Z",
      "details": {
        "dimensions": 768
      }
    },
    {
      "name": "CS30_SEARCH_COMPLETE",
      "timestamp": "2025-08-21T22:40:12.987Z",
      "details": {
        "resultsCount": 0,
        "timeMs": 290
      }
    },
    {
      "name": "CS30_NO_RELEVANT_RESULTS",
      "timestamp": "2025-08-21T22:40:12.987Z",
      "details": "No relevant CS30 results found"
    },
    {
      "name": "FLOW_COMPLETE",
      "timestamp": "2025-08-21T22:40:12.987Z",
      "details": {
        "timeMs": 22575,
        "hasCs30Response": false
      }
    }
  ],
  "cs30": {
    "collection": "cs30",
    "isAvailable": true,
    "collectionInfo": {
      "dimensions": 768,
      "distanceMetric": "Cosine",
      "hasIndexes": false,
      "config": {
        "params": {
          "vectors": {
            "size": 768,
            "distance": "Cosine",
            "on_disk": true
          },
          "shard_number": 1,
          "replication_factor": 1,
          "write_consistency_factor": 1,
          "on_disk_payload": true
        },
        "hnsw_config": {
          "m": 16,
          "ef_construct": 100,
          "full_scan_threshold": 10000,
          "max_indexing_threads": 0,
          "on_disk": true
        },
        "optimizer_config": {
          "deleted_threshold": 0.2,
          "vacuum_min_vector_number": 1000,
          "default_segment_number": 0,
          "max_segment_size": null,
          "memmap_threshold": null,
          "indexing_threshold": 20000,
          "flush_interval_sec": 50,
          "max_optimization_threads": null
        },
        "wal_config": {
          "wal_capacity_mb": 32,
          "wal_segments_ahead": 0
        },
        "quantization_config": null
      }
    },
    "samplePoints": [],
    "searchResults": [],
    "searchScores": [],
    "payloadStructure": {},
    "contextUsed": ""
  },
  "response": {
    "final": "Absolut. Das Verwalten von Anwendungsfehlern ist eine zentrale und tägliche Aufgabe in der Marktkommunikation (MaKo) der Energiewirtschaft. Es sorgt dafür, dass die automatisierten Prozesse zwischen den Marktpartnern (z.B. Lieferant, Netzbetreiber, Messstellenbetreiber) reibungslos funktionieren.\n\nIch gliedere das Thema für dich in die wichtigsten Aspekte:\n\n### 1. Das zentrale Werkzeug: Die APERAK-Nachricht\n\nDer wichtigste Mechanismus zur Meldung von Anwendungsfehlern ist die **APERAK** (Application Error and Acknowledgement Message).\n\n*   **Zweck:** Wenn ein Marktpartner eine Nachricht von dir erhält (z.B. eine Anmeldung über UTILMD) und diese fachlich oder formal nicht verarbeiten kann, schickt er dir eine APERAK zurück.\n*   **Inhalt:** Die APERAK enthält:\n    *   Eine Referenz auf deine ursprüngliche Nachricht.\n    *   Einen Fehlercode (z.B. \"Z01\" für \"Zählpunkt unbekannt\").\n    *   Einen Klartext, der den Fehler genauer beschreibt.\n*   **Abgrenzung zur CONTRL:** Die CONTRL-Nachricht bestätigt nur den syntaktisch korrekten Empfang einer EDIFACT-Datei. Die APERAK hingegen meldet einen Fehler bei der **inhaltlichen Verarbeitung** der Nachricht. Eine positive CONTRL und eine negative APERAK sind also ein häufiger Fall.\n\n---\n\n### 2. Der typische Prozess zur Fehlerverwaltung (Schritt für Schritt)\n\nWenn ein Anwendungsfehler auftritt (z.B. durch den Eingang einer APERAK), folgt in der Regel dieser Prozess:\n\n**Schritt 1: Identifikation & Monitoring**\n\n*   Dein System (z.B. SAP IS-U, Schleupen, Kisters) empfängt die APERAK.\n*   Ein automatisches Monitoring-System oder ein Sachbearbeiter im \"Clearing\" wird alarmiert",
    "withoutCs30": "Absolut. Das Verwalten von Anwendungsfehlern ist eine zentrale und tägliche Aufgabe in der Marktkommunikation (MaKo) der Energiewirtschaft. Es sorgt dafür, dass die automatisierten Prozesse zwischen den Marktpartnern (z.B. Lieferant, Netzbetreiber, Messstellenbetreiber) reibungslos funktionieren.\n\nIch gliedere das Thema für dich in die wichtigsten Aspekte:\n\n### 1. Das zentrale Werkzeug: Die APERAK-Nachricht\n\nDer wichtigste Mechanismus zur Meldung von Anwendungsfehlern ist die **APERAK** (Application Error and Acknowledgement Message).\n\n*   **Zweck:** Wenn ein Marktpartner eine Nachricht von dir erhält (z.B. eine Anmeldung über UTILMD) und diese fachlich oder formal nicht verarbeiten kann, schickt er dir eine APERAK zurück.\n*   **Inhalt:** Die APERAK enthält:\n    *   Eine Referenz auf deine ursprüngliche Nachricht.\n    *   Einen Fehlercode (z.B. \"Z01\" für \"Zählpunkt unbekannt\").\n    *   Einen Klartext, der den Fehler genauer beschreibt.\n*   **Abgrenzung zur CONTRL:** Die CONTRL-Nachricht bestätigt nur den syntaktisch korrekten Empfang einer EDIFACT-Datei. Die APERAK hingegen meldet einen Fehler bei der **inhaltlichen Verarbeitung** der Nachricht. Eine positive CONTRL und eine negative APERAK sind also ein häufiger Fall.\n\n---\n\n### 2. Der typische Prozess zur Fehlerverwaltung (Schritt für Schritt)\n\nWenn ein Anwendungsfehler auftritt (z.B. durch den Eingang einer APERAK), folgt in der Regel dieser Prozess:\n\n**Schritt 1: Identifikation & Monitoring**\n\n*   Dein System (z.B. SAP IS-U, Schleupen, Kisters) empfängt die APERAK.\n*   Ein automatisches Monitoring-System oder ein Sachbearbeiter im \"Clearing\" wird alarmiert",
    "onlyCs30": ""
  },
  "metrics": {
    "cs30SearchTime": 290,
    "cs30GenerationTime": 0,
    "totalProcessingTime": 22575
  }
}